LICENSE.txt
README.md
pyproject.toml
src/jijzept_solver/__init__.py
src/jijzept_solver/channel.py
src/jijzept_solver/config.py
src/jijzept_solver/deprecation.py
src/jijzept_solver/solve.py
src/jijzept_solver.egg-info/PKG-INFO
src/jijzept_solver.egg-info/SOURCES.txt
src/jijzept_solver.egg-info/dependency_links.txt
src/jijzept_solver.egg-info/requires.txt
src/jijzept_solver.egg-info/top_level.txt
src/jijzept_solver_proto/jijzept_solver_pb2.py
src/jijzept_solver_proto/jijzept_solver_pb2.pyi
src/jijzept_solver_proto/jijzept_solver_pb2_grpc.py
tests/test_config.py