Metadata-Version: 2.4
Name: jijzept_solver
Version: 1.2.0
Summary: A client for JijZept Solver API.
Author-email: "Jij Inc." <info@j-ij.com>
License: JijZept Solver Terms of Use
Requires-Python: >=3.9
License-File: LICENSE.txt
Requires-Dist: ommx<3.0.0,>=2.0.0
Requires-Dist: grpcio<2.0.0,>=1.69.0
Requires-Dist: certifi>=2025.0.0
Provides-Extra: dev
Requires-Dist: pytest; extra == "dev"
Requires-Dist: requests; extra == "dev"
Dynamic: license-file
